Metadata-Version: 2.1
Name: ktts
Version: 4.0
Summary: tts for python
Home-page: https://github.com/Jeyadevanjd/ktts/releases/
Author: Jeyadevan
Author-email: leejack17356@gmail.com
License: MIT
Platform: UNKNOWN
Classifier: License :: OSI Approved :: MIT License
Classifier: Programming Language :: Python :: 3
Classifier: Programming Language :: Python :: 3.7
